README.rst
setup.py
jsuite/__init__.py
jsuite/content.py
jsuite/count.py
jsuite/extract.py
jsuite.egg-info/PKG-INFO
jsuite.egg-info/SOURCES.txt
jsuite.egg-info/dependency_links.txt
jsuite.egg-info/requires.txt
jsuite.egg-info/top_level.txt
test/test_content.py
test/test_count.py
test/test_extract.py