Metadata-Version: 1.1
Name: jsuite
Version: 0.4.1
Summary: Parsing and manipulation tools for JATS XML files.
Home-page: https://github.com/schatten/jsuite
Author: Dipanjan Mukherjee
Author-email: dipanjan.mu@gmail.com
License: MIT
Keywords: xml parsing JATS tools
Platform: UNKNOWN
Classifier: Development Status :: 5 - Production/Stable
Classifier: Intended Audience :: Developers
Classifier: Topic :: Text Processing :: Markup :: XML
Classifier: License :: OSI Approved :: MIT License
Classifier: Programming Language :: Python :: 2
Classifier: Programming Language :: Python :: 2.7
